slacktoken/__init__.py
slacktoken/__main__.py
slacktoken/commands/__init__.py
slacktoken/commands/get.py
slacktoken/commands/version.py
slacktoken/cookies.py
slacktoken/decryptor.py
slacktoken/exceptions.py
slacktoken/slack_configuration.py
slacktoken/token.py
slacktoken/version.py
slacktoken-0.0.10.dist-info/METADATA
slacktoken-0.0.10.dist-info/WHEEL
slacktoken-0.0.10.dist-info/entry_points.txt
slacktoken-0.0.10.dist-info/RECORD
