Metadata-Version: 2.1
Name: slacktoken
Version: 0.0.10
Summary: A library for retrieving a Slack user token from an authenticated Slack application.
Home-page: https://github.com/chrisgavin/slacktoken/
License: BSD-2-Clause
Author: Chris Gavin
Author-email: chris@chrisgavin.me
Requires-Python: >=3.8,<4.0
Classifier: License :: OSI Approved :: BSD License
Classifier: Programming Language :: Python :: 3
Classifier: Programming Language :: Python :: 3.8
Classifier: Programming Language :: Python :: 3.9
Classifier: Programming Language :: Python :: 3.10
Classifier: Programming Language :: Python :: 3.11
Classifier: Programming Language :: Python :: 3.12
Classifier: Programming Language :: Python :: 3.13
Requires-Dist: PyGObject (>=3.42.1,<4.0.0) ; sys_platform == "linux"
Requires-Dist: cryptography (>=36.0.2,<44.0.0)
Requires-Dist: importlib-metadata
Requires-Dist: keyring (>=23.5,<26.0) ; sys_platform == "darwin"
Requires-Dist: pywin32 (>=304,<309) ; sys_platform == "win32"
Requires-Dist: requests
Requires-Dist: versio
Project-URL: Repository, https://github.com/chrisgavin/slacktoken/
